Workbook

Sheet trash_hauler_report
A1: Request Number | B1: Date Opened | C1: Request | D1: Description | E1: Incident Address | F1: Not | G1: Not | S1: Zip Code | T1: Trash Hauler | U1: Trash Route | V1: Council District | W1: State Plan X | X1: State Plan Y
A2: 25270 | B2: 43040 | C2: Trash - Backdoor | D2: house with the wheel chair ramp, they share driveway, in back driveway. 3817 Crouch Dr near NES light post is. 615-876-6274 | E2: 3817 Crouch Dr | F2: =SEARCH($G$1,D2,1) -> #VALUE! | G2: D2 | H2: 1) | S2: 37207 | T2: RED RIVER | U2: 3205 | V2: 2 | W2: 1727970.4 | X2: 686779.48
A3: 25274 | B3: 43040 | C3: Trash - Curbside/Alley Missed Pickup | D3: Curb/Trash miss Tuesday. | E3: 4028 Clarksville Pike | F3: =SEARCH($G$1,D3,1) -> #VALUE! | G3: =SEARCH($G$1,D3,1) -> #VALUE! | S3: 37218 | T3: RED RIVER | U3: 4202 | V3: 1 | W3: 1721259.4 | X3: 685444.8
A4: 25276 | B4: 43040 | C4: Trash - Curbside/Alley Missed Pickup | D4: Curb/trash miss Tuesday. | E4: 6528 Thunderbird Dr | F4: =SEARCH($G$1,D4,1) -> #VALUE! | G4: =SEARCH($G$1,D4,1) -> #VALUE! | S4: 37209 | T4: RED RIVER | U4: 4205 | V4: 20 | W4: 1707026.8 | X4: 659887.47
A5: 25307 | B5: 43040 | C5: Trash - Curbside/Alley Missed Pickup | D5: missed | E5: 2603 old matthews rd | F5: =SEARCH($G$1,D5,1) -> #VALUE! | G5: =SEARCH($G$1,D5,1) -> #VALUE! | S5: 37207 | T5: WASTE IND | U5: 2206 | V5: 2 | W5: 1735691.8 | X5: 685027.25
A6: 25312 | B6: 43040 | C6: Trash - Curbside/Alley Missed Pickup | D6: Missed the even side of the road. | E6: 604 croley dr | F6: =SEARCH($G$1,D6,1) -> #VALUE! | G6: =SEARCH($G$1,D6,1) -> #VALUE! | S6: 37209 | T6: RED RIVER | U6: 4203 | V6: 20 | W6: 1710185.8 | X6: 664205.1
A7: 25317 | B7: 43040 | C7: Trash Collection Complaint | D7: left trash cart in middle of driveway instead of at the backdoor pickup spot | E7: 3602 floral dr | F7: =SEARCH($G$1,D7,1) -> #VALUE! | G7: =SEARCH($G$1,D7,1) -> #VALUE! | S7: 37211 | T7: RED RIVER | U7: 4304 | V7: 16 | W7: 1751660.2 | X7: 643215.2
A8: 25325 | B8: 43040 | C8: Damage to Property | D8: Trash/emptied Wednesday & now metal black-mailbox damage. customer wants call back and fix and replace. | E8: 4721 Chalmers Dr | F8: =SEARCH($G$1,D8,1) -> #VALUE! | G8: =SEARCH($G$1,D8,1) -> #VALUE! | S8: 37215 | T8: RED RIVER | U8: 3303 | V8: 34 | W8: 1726301 | X8: 637078.4
A9: 25327 | B9: 43040 | C9: Trash Collection Complaint | D9: Trash out on time, miss again Tuesday. ALLEY | E9: 1816 Jo Johnston Ave | F9: =SEARCH($G$1,D9,1) -> #VALUE! | G9: =SEARCH($G$1,D9,1) -> #VALUE! | S9: 37203 | T9: METRO | U9: 9208 | V9: 21 | W9: 1731459.4 | X9: 666013.6
A10: 25330 | B10: 43040 | C10: Trash - Curbside/Alley Missed Pickup | D10: Missed. | E10: 4484 Lavergne Couchville Pike | F10: =SEARCH($G$1,D10,1) -> #VALUE! | G10: =SEARCH($G$1,D10,1) -> #VALUE! | S10: 37013 | T10: RED RIVER | U10: 4210 | V10: 33 | W10: 1794533.5 | X10: 618749.34
A11: 25331 | B11: 43040 | C11: Trash - Curbside/Alley Missed Pickup | D11: Trash missed Tuesday again, ALLEY | E11: 1206 Ireland St | F11: =SEARCH($G$1,D11,1) -> #VALUE! | G11: =SEARCH($G$1,D11,1) -> #VALUE! | S11: 37208 | T11: METRO | U11: 9208 | V11: 19 | W11: 1733029.5 | X11: 668762.64
A12: 25341 | B12: 43040 | C12: Trash - Curbside/Alley Missed Pickup | D12: Missed trash pickup - resident has at curb for pick up today received back door form on 10/30/2017 is still in interoffice mail pickup since 10/30 | E12: 3113 HYDES FERRY RD | F12: =SEARCH($G$1,D12,1) -> #VALUE! | G12: =SEARCH($G$1,D12,1) -> #VALUE! | S12: 37218 | T12: RED RIVER | U12: 4204 | V12: 2 | W12: 1721577.8 | X12: 676018.4
A13: 25350 | B13: 43040 | C13: Trash Collection Complaint | D13: Missed- 4th week in a row. | E13: 3210 Whites Creek Pike | F13: =SEARCH($G$1,D13,1) -> #VALUE! | G13: =SEARCH($G$1,D13,1) -> #VALUE! | S13: 37207 | T13: RED RIVER | U13: 3201 | V13: 3 | W13: 1726433 | X13: 691919.2
A14: 25359 | B14: 43040 | C14: Trash - Curbside/Alley Missed Pickup | D14: Missed. Does not have access to alley. | E14: 830 Meridian St | F14: =SEARCH($G$1,D14,1) -> 14 | G14: =SEARCH($G$1,D14,1) -> 14 | S14: 37207 | T14: METRO | U14: 9207 | V14: 5 | W14: 1741744.7 | X14: 675328.67
... A21: 25454 | B21: 43040 | C21: Trash - Curbside/Alley Missed Pickup | D21: Missed. | E21: 449 Westboro Dr | F21: =SEARCH($G$1,D21,1) -> #VALUE! | G21: =SEARCH($G$1,D21,1) -> #VALUE! | S21: 37209 | T21: RED RIVER | U21: 4201 | V21: 20 | W21: 1710615.1 | X21: 661992.33
A22: 25465 | B22: 43040 | C22: Trash Collection Complaint | D22: A resident is complaining that a trash truck ran a red light through a school zone at Davidson Academy. The truck number is 4887AH. | E22: 1414 Old Hickory Blvd | F22: =SEARCH($G$1,D22,1) -> #VALUE! | G22: =SEARCH($G$1,D22,1) -> #VALUE! | S22: 37207 | V22: 3 | W22: 1738737 | X22: 711231.8
A23: 25469 | B23: 43040 | C23: Trash - Curbside/Alley Missed Pickup | D23: Our trash was not picked up today, Wed, Nov 1. It was out by 7 am and our neighbors trash was picked up but ours was not. | E23: 117 Lafayette Ct | F23: =SEARCH($G$1,D23,1) -> 15 | G23: =SEARCH($G$1,D23,1) -> 15 | S23: 37205 | T23: RED RIVER | U23: 1302 | V23: 23 | W23: 1713465 | X23: 644882.4
A24: 25471 | B24: 43040 | C24: Trash - Curbside/Alley Missed Pickup | D24: Alley trash miss Tuesday, also others as well, out on time. | E24: 1904 MeHarry Blvd | F24: =SEARCH($G$1,D24,1) -> #VALUE! | G24: =SEARCH($G$1,D24,1) -> #VALUE! | S24: 37208 | T24: METRO | U24: 9208 | V24: 21 | W24: 1730048.1 | X24: 668927.19
A25: 25474 | B25: 43040 | C25: Trash - Curbside/Alley Missed Pickup | D25: Customer says backdoor pickup was missed the past 2 weeks | E25: 1144 Sewanee Rd | F25: =SEARCH($G$1,D25,1) -> #VALUE! | G25: =SEARCH($G$1,D25,1) -> #VALUE! | S25: 37220 | T25: RED RIVER | U25: 3302 | V25: 34 | W25: 1731663.4 | X25: 639182.4
A26: 25496 | B26: 43040 | C26: Trash - Curbside/Alley Missed Pickup | D26: Missed pickup | E26: 1815 WOODMONT BLVD | F26: =SEARCH($G$1,D26,1) -> #VALUE! | G26: =SEARCH($G$1,D26,1) -> #VALUE! | S26: 37215 | T26: RED RIVER | U26: 3305 | V26: 25 | W26: 1730532.2 | X26: 648861.63
A27: 25506 | B27: 43040 | C27: Trash - Curbside/Alley Missed Pickup | D27: Missed. | E27: 405 Page Rd | F27: =SEARCH($G$1,D27,1) -> #VALUE! | G27: =SEARCH($G$1,D27,1) -> #VALUE! | S27: 37205 | T27: RED RIVER | U27: 1302 | V27: 34 | W27: 1711546.6 | X27: 639925.6
A28: 25507 | B28: 43040 | C28: Trash - Curbside/Alley Missed Pickup | D28: Missed pickup | E28: 4722 DANBY DR | F28: =SEARCH($G$1,D28,1) -> #VALUE! | G28: =SEARCH($G$1,D28,1) -> #VALUE! | S28: 37211 | T28: RED RIVER | U28: 4302 | V28: 26 | W28: 1748482.6 | X28: 636882.4
A29: 25508 | B29: 43040 | C29: Trash Collection Complaint | D29: missed. Neighbor missed as well-say she is at a dead end and she is constantly missed. She understands it is hard for the driver to turn around but she doesn't want to have to call all the time. | E29: 2812 27TH AVE S | F29: =SEARCH($G$1,D29,1) -> #VALUE! | G29: =SEARCH($G$1,D29,1) -> #VALUE! | S29: 37212 | T29: RED RIVER | U29: 2305 | V29: 18 | W29: 1729022.3 | X29: 652985.68
A30: 25509 | B30: 43040 | C30: Trash - Curbside/Alley Missed Pickup | D30: cust says entire street was missed | E30: 4506 DAKOTA AVE | F30: =SEARCH($G$1,D30,1) -> #VALUE! | G30: =SEARCH($G$1,D30,1) -> #VALUE! | S30: 37209 | T30: RED RIVER | U30: 1308 | V30: 24 | W30: 1720100.2 | X30: 661552.8
A31: 25511 | B31: 43040 | C31: Trash - Curbside/Alley Missed Pickup | D31: Missed. | E31: 259 Sunrise Ave | F31: =SEARCH($G$1,D31,1) -> #VALUE! | G31: =SEARCH($G$1,D31,1) -> #VALUE! | S31: 37211 | T31: RED RIVER | U31: 4304 | V31: 16 | W31: 1750609.6 | X31: 645187.68
A32: 25512 | B32: 43040 | C32: Trash - Curbside/Alley Missed Pickup | D32: cust says entire street was missed | E32: 4311 dakota ave | F32: =SEARCH($G$1,D32,1) -> #VALUE! | G32: =SEARCH($G$1,D32,1) -> #VALUE! | S32: 37209 | T32: RED RIVER | U32: 1308 | V32: 24 | W32: 1720100.2 | X32: 661552.8
A33: 25515 | B33: 43040 | C33: Trash - Curbside/Alley Missed Pickup | D33: Missed. Cart is still out | E33: 4029 Graybar Ct | F33: =SEARCH($G$1,D33,1) -> #VALUE! | G33: =SEARCH($G$1,D33,1) -> #VALUE! | S33: 37215 | T33: RED RIVER | U33: 3305 | V33: 25 | W33: 1729986.3 | X33: 648821.43
A34: 25517 | B34: 43040 | C34: Trash - Curbside/Alley Missed Pickup | D34: Missed. | E34: 524 Harding Pl | F34: =SEARCH($G$1,D34,1) -> #VALUE! | G34: =SEARCH($G$1,D34,1) -> #VALUE! | S34: 37211 | T34: RED RIVER | U34: 4302 | V34: 26 | W34: 1751209 | X34: 635651.2
... A44: 25575 | B44: 43041 | C44: Trash - Curbside/Alley Missed Pickup | D44: missed pick up | E44: 346 lynn dr | F44: =SEARCH($G$1,D44,1) -> #VALUE! | G44: =SEARCH($G$1,D44,1) -> #VALUE! | S44: 37211 | T44: RED RIVER | U44: 4302 | V44: 26 | W44: 1747944.1 | X44: 637187.8
A45: 25577 | B45: 43041 | C45: Trash - Curbside/Alley Missed Pickup | D45: trash missed pick up - others missed in area | E45: 4205 arundel ct | F45: =SEARCH($G$1,D45,1) -> #VALUE! | G45: =SEARCH($G$1,D45,1) -> #VALUE! | S45: 37215 | T45: RED RIVER | U45: 2303S | V45: 25 | W45: 1721425 | X45: 648442.07
A46: 25578 | B46: 43041 | C46: Trash Collection Complaint | D46: Curb/Trash missed Whole street, check for other streets as well seen carts still out. Wednesday. Has to keep calling. wants to know why? | E46: 204 Channelkirk Ln | F46: =SEARCH($G$1,D46,1) -> #VALUE! | G46: =SEARCH($G$1,D46,1) -> #VALUE! | S46: 37215 | T46: RED RIVER | U46: 3305 | V46: 25 | W46: 1729598.7 | X46: 648513.73
A47: 25585 | B47: 43041 | C47: Trash - Curbside/Alley Missed Pickup | D47: Curb/Trash miss Wednesday | E47: 200 Channelkirk Ln | F47: =SEARCH($G$1,D47,1) -> #VALUE! | G47: =SEARCH($G$1,D47,1) -> #VALUE! | S47: 37215 | T47: RED RIVER | U47: 3305 | V47: 25 | W47: 1729513.3 | X47: 648495.57
A48: 25586 | B48: 43041 | C48: Trash - Curbside/Alley Missed Pickup | D48: Missed pickup | E48: 4311 dakota ave | F48: =SEARCH($G$1,D48,1) -> #VALUE! | G48: =SEARCH($G$1,D48,1) -> #VALUE! | S48: 37209 | T48: RED RIVER | U48: 1308 | V48: 24 | W48: 1720742.7 | X48: 661438.82
A49: 25587 | B49: 43041 | C49: Trash - Curbside/Alley Missed Pickup | D49: MISSED TRASH CHECK FOR OTHERS ALSO MISSED CURB | E49: 101 Westover Park Ct | F49: =SEARCH($G$1,D49,1) -> #VALUE! | G49: =SEARCH($G$1,D49,1) -> #VALUE! | S49: 37215 | T49: RED RIVER | U49: 3305S | V49: 25 | W49: 1729295.5 | X49: 644211.6
A50: 25588 | B50: 43041 | C50: Trash Collection Complaint | D50: Missed says it has happened numerous times and she is upset. wants Supervisor to call her. | E50: 201 Channelkirk Ln | F50: =SEARCH($G$1,D50,1) -> #VALUE! | G50: =SEARCH($G$1,D50,1) -> #VALUE! | S50: 37215 | T50: RED RIVER | U50: 3305 | V50: 25 | W50: 1729536.8 | X50: 648641.9
A51: 25592 | B51: 43041 | C51: Trash - Curbside/Alley Missed Pickup | D51: Missed pickup; cust says trash is missed once a month | E51: 205 Channelkirk Ln | F51: =SEARCH($G$1,D51,1) -> #VALUE! | G51: =SEARCH($G$1,D51,1) -> #VALUE! | S51: 37215 | T51: RED RIVER | U51: 3305 | V51: 25 | W51: 1729610.5 | X51: 648595.97
A52: 25593 | B52: 43041 | C52: Trash - Curbside/Alley Missed Pickup | D52: New resident, trash missed 2 weeks in a row | E52: 4309 Lone Oak Rd | F52: =SEARCH($G$1,D52,1) -> #VALUE! | G52: =SEARCH($G$1,D52,1) -> #VALUE! | S52: 37215 | T52: RED RIVER | U52: 3305 | V52: 25 | W52: 1729234.8 | X52: 643478.25
A53: 25594 | B53: 43041 | C53: Trash - Curbside/Alley Missed Pickup | D53: Missed entire alley | E53: 4507 Nevada Ave | F53: =SEARCH($G$1,D53,1) -> #VALUE! | G53: =SEARCH($G$1,D53,1) -> #VALUE! | S53: 37209 | T53: RED RIVER | U53: 1308 | V53: 24 | W53: 1720021.8 | X53: 661789.6
A54: 25606 | B54: 43041 | C54: Trash - Curbside/Alley Missed Pickup | D54: Missed pickup | E54: 3012 Sunnyview Ct | F54: =SEARCH($G$1,D54,1) -> #VALUE! | G54: =SEARCH($G$1,D54,1) -> #VALUE! | S54: 37218 | T54: RED RIVER | U54: 3204 | V54: 1 | W54: 1724135.7 | X54: 690902.4
A55: 25653 | B55: 43041 | C55: Trash - Curbside/Alley Missed Pickup | D55: missed the entire street | E55: 118 WESTOVER PARK CT | F55: =SEARCH($G$1,D55,1) -> #VALUE! | G55: =SEARCH($G$1,D55,1) -> #VALUE! | S55: 37215 | T55: RED RIVER | U55: 3305S | V55: 25 | W55: 1728948 | X55: 644353.07
A56: 25674 | B56: 43041 | C56: Trash - Curbside/Alley Missed Pickup | D56: Missed pick-up | E56: 607 40th Ave N | F56: =SEARCH($G$1,D56,1) -> #VALUE! | G56: =SEARCH($G$1,D56,1) -> #VALUE! | S56: 37209 | T56: RED RIVER | U56: 1309 | V56: 21 | W56: 1722065.8 | X56: 664354.4
A57: 25692 | B57: 43041 | C57: Trash - Backdoor | D57: Backdoor/miss for last Friday. Does not understand why? | E57: 3041 Fieldstone Dr | F57: =SEARCH($G$1,D57,1) -> 37 | G57: =SEARCH($G$1,D57,1) -> 37 | S57: 37013 | T57: RED RIVER | U57: 3504 | V57: 29 | W57: 1785677.2 | X57: 633139.25
A58: 25694 | B58: 43041 | C58: Trash - Curbside/Alley Missed Pickup | D58: Missed. | E58: 1413 Montgomery Ave | F58: =SEARCH($G$1,D58,1) -> #VALUE! | G58: =SEARCH($G$1,D58,1) -> #VALUE! | S58: 37207 | T58: METRO | U58: 9203 | V58: 5 | W58: 1745688.2 | X58: 679130.4
A59: 25702 | B59: 43041 | C59: Trash - Curbside/Alley Missed Pickup | D59: missed pick up | E59: 962 battery ln | F59: =SEARCH($G$1,D59,1) -> #VALUE! | G59: =SEARCH($G$1,D59,1) -> #VALUE! | S59: 37220 | T59: RED RIVER | U59: 3302 | V59: 25 | W59: 1734959.4 | X59: 639839.2
A60: 25717 | B60: 43041 | C60: Trash - Curbside/Alley Missed Pickup | D60: Trash/Miss Alley # 2088 Wednesday pick up UNIT-B Between Page Rd & Heady Dr | E60: 103 Page Rd | F60: =SEARCH($G$1,D60,1) -> #VALUE! | G60: =SEARCH($G$1,D60,1) -> #VALUE! | S60: 37205 | T60: RED RIVER | U60: 1302 | V60: 34 | W60: 1711419.2 | X60: 644106.79
A61: 25733 | B61: 43041 | C61: Trash - Curbside/Alley Missed Pickup | D61: Missed pickup | E61: 905 woodmont blvd | F61: =SEARCH($G$1,D61,1) -> #VALUE! | G61: =SEARCH($G$1,D61,1) -> #VALUE! | S61: 37204 | T61: RED RIVER | U61: 4305 | V61: 25 | W61: 1737879 | X61: 647550.36
A62: 25736 | B62: 43041 | C62: Trash - Curbside/Alley Missed Pickup | D62: Missed. | E62: 114 Lasalle Ct B | F62: =SEARCH($G$1,D62,1) -> #VALUE! | G62: =SEARCH($G$1,D62,1) -> #VALUE! | S62: 37205 | T62: RED RIVER | U62: 1302 | V62: 23 | W62: 1713697.1 | X62: 644931.82
A63: 25743 | B63: 43041 | C63: Trash Collection Complaint | D63: Resident is very upset- Red River emptied only one of the 2 brown carts he had out, truck driver clamps both together all the time, he needs to do one at the time. | E63: 732 Ridgeview Ct | F63: =SEARCH($G$1,D63,1) -> #VALUE! | G63: =SEARCH($G$1,D63,1) -> #VALUE! | S63: 37013 | T63: RED RIVER | U63: 4403 | V63: 31 | W63: 1759010.6 | X63: 619983.2
A64: 25753 | B64: 43041 | C64: Trash - Curbside/Alley Missed Pickup | D64: Curb trash miss for Wednesday. Everyone else was emptied. Small business" non- profit | E64: 2323 Merry St | F64: =SEARCH($G$1,D64,1) -> #VALUE! | G64: =SEARCH($G$1,D64,1) -> #VALUE! | S64: 37208 | T64: METRO | U64: 9303 | V64: 21 | W64: 1728796.4 | X64: 665734.06
A65: 25775 | B65: 43041 | C65: Trash - Backdoor | D65: Missed trash pickup said has been picking up behind the gate for 26 years (615) 333-0065 | E65: 4625 long br | F65: =SEARCH($G$1,D65,1) -> #VALUE! | G65: =SEARCH($G$1,D65,1) -> #VALUE! | S65: 37013 | T65: RED RIVER | U65: 4505 | V65: 28 | W65: 1770350.4 | X65: 634143.87
A66: 25780 | B66: 43041 | C66: Trash Collection Complaint | D66: Missed again picked up everyone except her does not understand why keep missing (615) 753-1696 | E66: 816 Elissa Dr | F66: =SEARCH($G$1,D66,1) -> 49 | G66: =SEARCH($G$1,D66,1) -> 49 | S66: 37217 | T66: RED RIVER | U66: 1401 | V66: 13 | W66: 1760730.6 | X66: 657712.8
A67: 25784 | B67: 43041 | C67: Trash Collection Complaint | D67: Customer says it was missed again | E67: 608 CLEVELAND ST | F67: =SEARCH($G$1,D67,1) -> #VALUE! | G67: =SEARCH($G$1,D67,1) -> #VALUE! | S67: 37207 | T67: METRO | U67: 9203 | V67: 5 | W67: 1743925.8 | X67: 675188
... A71: 25793 | B71: 43041 | C71: Trash - Curbside/Alley Missed Pickup | D71: Missed. | E71: 4104 Coleridge Dr | F71: =SEARCH($G$1,D71,1) -> #VALUE! | G71: =SEARCH($G$1,D71,1) -> #VALUE! | S71: 37013 | T71: RED RIVER | U71: 3404 | V71: 30 | W71: 1763188.2 | X71: 628038.4
A72: 25800 | B72: 43041 | C72: Trash - Curbside/Alley Missed Pickup | D72: missed trash - others missed in area | E72: 362 ardsley pl | F72: =SEARCH($G$1,D72,1) -> #VALUE! | G72: =SEARCH($G$1,D72,1) -> #VALUE! | S72: 37215 | T72: RED RIVER | U72: 3301S | V72: 34 | W72: 1723730.6 | X72: 641638.38
A73: 25802 | B73: 43041 | C73: Trash - Backdoor | D73: Missed. | E73: 4828 Cimarron Way | F73: =SEARCH($G$1,D73,1) -> #VALUE! | G73: =SEARCH($G$1,D73,1) -> #VALUE! | S73: 37013 | T73: RED RIVER | U73: 3404 | V73: 30 | W73: 1766186.6 | X73: 629785.6
A74: 25808 | B74: 43041 | C74: Trash - Curbside/Alley Missed Pickup | D74: cust says missed pickup again | E74: 496 Whispering Hills Dr | F74: =SEARCH($G$1,D74,1) -> #VALUE! | G74: =SEARCH($G$1,D74,1) -> #VALUE! | S74: 37211 | T74: RED RIVER | U74: 3401 | V74: 27 | W74: 1755478.4 | X74: 629550.79
A75: 25809 | B75: 43041 | C75: Trash - Curbside/Alley Missed Pickup | D75: Robin Springs Road missed! | E75: Robin Springs Rd | F75: =SEARCH($G$1,D75,1) -> #VALUE! | G75: =SEARCH($G$1,D75,1) -> #VALUE! | S75: 37220 | T75: RED RIVER | U75: 3302S | V75: 34 | W75: 1732449.8 | X75: 639784.4
A76: 25816 | B76: 43041 | C76: Trash - Curbside/Alley Missed Pickup | D76: trash out on Tuesday night for Wednesday pickup, other trash cans were emptied, mine was skipped. full needs emptied. | E76: 1711 Glen Echo Rd A | F76: =SEARCH($G$1,D76,1) -> #VALUE! | G76: =SEARCH($G$1,D76,1) -> #VALUE! | S76: 37215 | T76: RED RIVER | U76: 3305 | V76: 25 | W76: 1730968.2 | X76: 646848.13
A77: 25821 | B77: 43041 | C77: Trash Collection Complaint | D77: Trash container out night before pickup in same location as previous 25 years. Trash was not picked up as scheduled Thursday. Would like trash pick up week as per property taxes. I also see my neighbors trash cans still out. I presume they have not had pickup either. By the way the double negatives in the questions below are confusing. I had bagged garbage, no recycling and no yard waste. | E77: 611 Farrell Pkwy | F77: =SEARCH($G$1,D77,1) -> 90 | G77: =SEARCH($G$1,D77,1) -> 90 | S77: 37220 | T77: RED RIVER | U77: 2403 | V77: 26 | W77: 1742604.2 | X77: 634061.6
A78: 25825 | B78: 43042 | C78: Trash - Curbside/Alley Missed Pickup | D78: Curb Trash missed Thursday. Duplex | E78: 531 Cathy Jo Cir | F78: =SEARCH($G$1,D78,1) -> #VALUE! | G78: =SEARCH($G$1,D78,1) -> #VALUE! | S78: 37211 | T78: RED RIVER | U78: 1404 | V78: 26 | W78: 1756294.8 | X78: 641849.91
A79: 25855 | B79: 43042 | C79: Trash - Curbside/Alley Missed Pickup | D79: Can i get my trash collection started? Online, it says that there are no services started even through I have the trash and recycle receptacles. My trash has not been picked up for a few weeks. Thanks. | E79: 427 West Bend Dr | F79: =SEARCH($G$1,D79,1) -> 159 | G79: =SEARCH($G$1,D79,1) -> 159 | S79: 37209 | T79: RED RIVER | U79: 4201 | V79: 20 | W79: 1711210.2 | X79: 661853.11
A80: 25858 | B80: 43042 | C80: Trash - Backdoor | D80: Missed- she said her grandson was over yesterday and he told her it was full. She needs it picked up | E80: 2005 Lebanon Pike | F80: =SEARCH($G$1,D80,1) -> #VALUE! | G80: =SEARCH($G$1,D80,1) -> #VALUE! | S80: 37210 | T80: RED RIVER | U80: 1504 | V80: 15 | W80: 1760561.8 | X80: 665276
A81: 25862 | B81: 43042 | C81: Trash Collection Complaint | D81: Trash missed last Thursday. Does not understand why? Curb please call 513-403-0759 other missed hub tickets ticket # 23455,20137,16881,13660,9921 | E81: 5900 Cloverland Dr | F81: =SEARCH($G$1,D81,1) -> 34 | G81: =SEARCH($G$1,D81,1) -> 34 | S81: 37027 | T81: RED RIVER | U81: 4401 | V81: 4 | W81: 1745205 | X81: 619088.8
A82: 25864 | B82: 43042 | C82: Trash Collection Complaint | D82: missed pick up - please call (615) 519-3192 wants to know why she is being missed | E82: 115 Rosa L Parks BLvd | F82: =SEARCH($G$1,D82,1) -> #VALUE! | G82: =SEARCH($G$1,D82,1) -> #VALUE! | S82: 37203 | V82: 19 | W82: 1737457.8 | X82: 665597.6
A83: 25866 | B83: 43042 | C83: Trash Collection Complaint | D83: caller upset states trash never runs that early, alley. Trash/cart full and wants cart emptied. UNIT-A | E83: 1112 Joseph Ave A | F83: =SEARCH($G$1,D83,1) -> #VALUE! | G83: =SEARCH($G$1,D83,1) -> #VALUE! | S83: 37207 | T83: METRO | U83: 9207 | V83: 5 | W83: 1740730.6 | X83: 677098.4
A84: 25882 | B84: 43042 | C84: Trash Collection Complaint | D84: not putting carts back where they got them lids left open carts on ground ...2 complaint see ticket CW 904806 615-975-1015 please call | E84: 1800 fatherland st | F84: =SEARCH($G$1,D84,1) -> 1 | G84: =SEARCH($G$1,D84,1) -> 1 | S84: 37206 | T84: METRO | U84: 9508 | V84: 6 | W84: 1750537 | X84: 670416.8
A85: 25883 | B85: 43042 | C85: Trash - Curbside/Alley Missed Pickup | D85: Curb 2 trash/carts miss Wednesday. | E85: 615 39th Ave N | F85: =SEARCH($G$1,D85,1) -> #VALUE! | G85: =SEARCH($G$1,D85,1) -> #VALUE! | S85: 37209 | T85: RED RIVER | U85: 1309 | V85: 21 | W85: 1722565.8 | X85: 664590.4
A86: 25924 | B86: 43042 | C86: Trash - Curbside/Alley Missed Pickup | D86: trash not picked up on Wednesday 11/1/17. Still there today, 11/3/17. | E86: 6532 cornwall ct | F86: =SEARCH($G$1,D86,1) -> 7 | G86: =SEARCH($G$1,D86,1) -> 7 | S86: 37205 | T86: RED RIVER | U86: 1301 | V86: 23 | W86: 1702976.2 | X86: 648132
A87: 25931 | B87: 43042 | C87: Trash - Curbside/Alley Missed Pickup | D87: Missed. | E87: 1801 Shelby Ave B | F87: =SEARCH($G$1,D87,1) -> #VALUE! | G87: =SEARCH($G$1,D87,1) -> #VALUE! | S87: 37206 | T87: METRO | U87: 9508 | V87: 6 | W87: 1750414.6 | X87: 669480
A88: 25937 | B88: 43042 | C88: Trash - Backdoor | D88: Has been in the hospital and waiver expired. | E88: 4225 Eatons Creek Rd | F88: =SEARCH($G$1,D88,1) -> #VALUE! | G88: =SEARCH($G$1,D88,1) -> #VALUE! | S88: 37218 | T88: RED RIVER | U88: 3203 | V88: 1 | W88: 1713335.4 | X88: 685777.6
A89: 25941 | B89: 43042 | C89: Trash Collection Complaint | D89: Missed again. Has had multiple issues with the route. Needs her trash picked up | E89: 1300 Rural Hill Rd | F89: =SEARCH($G$1,D89,1) -> #VALUE! | G89: =SEARCH($G$1,D89,1) -> #VALUE! | S89: 37013 | T89: RED RIVER | U89: 4504 | V89: 32 | W89: 1777932.2 | X89: 628763.2
A90: 25947 | B90: 43042 | C90: Trash - Curbside/Alley Missed Pickup | D90: missed pick up - others missed in area cart sits on Farrell Pkwy side of home | E90: 5001 Stillwood dr | F90: =SEARCH($G$1,D90,1) -> #VALUE! | G90: =SEARCH($G$1,D90,1) -> #VALUE! | S90: 37220 | T90: RED RIVER | U90: 2403 | V90: 26 | W90: 1743063.4 | X90: 633874.4
A91: 25949 | B91: 43042 | C91: Trash - Curbside/Alley Missed Pickup | D91: Curb Trash/Miss Thursday. {Dead End} | E91: 5040 Mclendon Dr | F91: =SEARCH($G$1,D91,1) -> #VALUE! | G91: =SEARCH($G$1,D91,1) -> #VALUE! | S91: 37013 | T91: RED RIVER | U91: 3404 | V91: 30 | W91: 1764866.5 | X91: 627175.46
A92: 25951 | B92: 43042 | C92: Trash - Backdoor | D92: never gets picked up please pick her up has tons of trash {Thursday} | E92: 15482 Old Hickory Blvd | F92: =SEARCH($G$1,D92,1) -> #VALUE! | G92: =SEARCH($G$1,D92,1) -> #VALUE! | S92: 37211 | T92: RED RIVER | U92: 4402 | V92: 27 | W92: 1751222.2 | X92: 621945.53
A93: 25963 | B93: 43042 | C93: Trash - Curbside/Alley Missed Pickup | D93: missed pick up - others missed in area | E93: 5209 nevada ave | F93: =SEARCH($G$1,D93,1) -> #VALUE! | G93: =SEARCH($G$1,D93,1) -> #VALUE! | S93: 37209 | T93: RED RIVER | U93: 1308 | V93: 24 | W93: 1717357 | X93: 661694.4
A94: 25968 | B94: 43042 | C94: Trash - Backdoor | D94: missing every other week- resident is upset. | E94: 2413 ravine dr | F94: =SEARCH($G$1,D94,1) -> #VALUE! | G94: =SEARCH($G$1,D94,1) -> #VALUE! | S94: 37217 | T94: RED RIVER | U94: 2505 | V94: 29 | W94: 1779724.9 | X94: 637970.05
... A98: 25976 | B98: 43042 | C98: Trash - Curbside/Alley Missed Pickup | D98: missed pick up - said happens often | E98: 2205 woodmont blvd | F98: =SEARCH($G$1,D98,1) -> #VALUE! | G98: =SEARCH($G$1,D98,1) -> #VALUE! | S98: 37215 | T98: RED RIVER | U98: 2305 | V98: 25 | W98: 1727989.9 | X98: 649157.29
A99: 25980 | B99: 43042 | C99: Trash Collection Complaint | D99: While cleaning the alley behind 1619 Heiman St, someone from the crew had a weed trimmer and cut some pine cypress trees that the customer was growing | E99: 1619 HEIMAN ST | F99: =SEARCH($G$1,D99,1) -> #VALUE! | G99: =SEARCH($G$1,D99,1) -> #VALUE! | S99: 37208 | V99: 21 | W99: 1730987.9 | X99: 670217.56
A100: 25982 | B100: 43042 | C100: Trash Collection Complaint | D100: Trash/carts sit's on side alley, missed last week. Thursday still full. {construction but recycle/guys pickup yesterday. | E100: 1209 Linden Ave | F100: =SEARCH($G$1,D100,1) -> #VALUE! | G100: =SEARCH($G$1,D100,1) -> #VALUE! | S100: 37212 | T100: METRO | U100: 9403 | V100: 18 | W100: 1735176.2 | X100: 654041.48
A101: 25985 | B101: 43042 | C101: Trash Collection Complaint | D101: Missed- neighbor was also skipped. | E101: 641 Truxton Ct | F101: =SEARCH($G$1,D101,1) -> #VALUE! | G101: =SEARCH($G$1,D101,1) -> #VALUE! | S101: 37214 | T101: RED RIVER | U101: 2501 | V101: 14 | W101: 1778863.4 | X101: 663667.2
A102: 25987 | B102: 43042 | C102: Trash - Curbside/Alley Missed Pickup | D102: Missed | E102: 1609 Lillian St | F102: =SEARCH($G$1,D102,1) -> #VALUE! | G102: =SEARCH($G$1,D102,1) -> #VALUE! | S102: 37206 | T102: METRO | U102: 9506 | V102: 6 | W102: 1749557.8 | X102: 670298.4
A103: 25988 | B103: 43042 | C103: Trash - Curbside/Alley Missed Pickup | D103: customer had 2 trash carts, but only one of them was emptied | E103: 3913 Tea Garden Way | F103: =SEARCH($G$1,D103,1) -> #VALUE! | G103: =SEARCH($G$1,D103,1) -> #VALUE! | S103: 37013 | T103: RED RIVER | U103: 3504 | V103: 33 | W103: 1787799.3 | X103: 631948.9
A104: 26009 | B104: 43042 | C104: Trash - Curbside/Alley Missed Pickup | D104: missed pickup | E104: 1009 Southside Ave B | F104: =SEARCH($G$1,D104,1) -> #VALUE! | G104: =SEARCH($G$1,D104,1) -> #VALUE! | S104: 37203 | T104: METRO | U104: 9407 | V104: 17 | W104: 1737251.7 | X104: 660570.71
A105: 26012 | B105: 43042 | C105: Trash Collection Complaint | D105: While cleaning the alley behind 1619 Heiman St, someone from the crew had a weed trimmer and cut some pine cypress trees that the customer was growing | E105: 1619 HEIMAN ST | F105: =SEARCH($G$1,D105,1) -> #VALUE! | G105: =SEARCH($G$1,D105,1) -> #VALUE! | S105: 37208 | T105: RED RIVER | U105: 3206 | V105: 21 | W105: 1730987.9 | X105: 670217.56
A106: 26014 | B106: 43042 | C106: Trash Collection Complaint | D106: file complaint trash is not getting pick up, wants to know why? Wednesday missed again. Curb | E106: 940 Battlefield Dr | F106: =SEARCH($G$1,D106,1) -> 25 | G106: =SEARCH($G$1,D106,1) -> 25 | S106: 37204 | T106: RED RIVER | U106: 4305 | V106: 25 | W106: 1736675 | X106: 649463.33
A107: 26026 | B107: 43042 | C107: Trash - Curbside/Alley Missed Pickup | D107: missed pickup for the street | E107: 4316 Summercrest Blvd 404 | F107: =SEARCH($G$1,D107,1) -> #VALUE! | G107: =SEARCH($G$1,D107,1) -> #VALUE! | S107: 37013 | T107: RED RIVER | U107: 4510 | V107: 32 | W107: 1785751.4 | X107: 625659.63
A108: 26027 | B108: 43042 | C108: Trash - Curbside/Alley Missed Pickup | D108: missed pick up | E108: 1316 hawkins st | F108: =SEARCH($G$1,D108,1) -> #VALUE! | G108: =SEARCH($G$1,D108,1) -> #VALUE! | S108: 37203 | T108: METRO | U108: 9405 | V108: 19 | W108: 1735750.6 | X108: 661916.86
A109: 26029 | B109: 43042 | C109: Trash Collection Complaint | D109: Says that the crew always leaves the cart in the middle of the road this time they left it in front of the mailbox and the mailman is unable to leave his mail. Would appreciate it if we put the cart back where he leaves it. Called about this last week and they did the exact same thing this week. | E109: 2127 Burns St | F109: =SEARCH($G$1,D109,1) -> #VALUE! | G109: =SEARCH($G$1,D109,1) -> #VALUE! | S109: 37216 | T109: METRO | U109: 9505 | V109: 7 | W109: 1753328.2 | X109: 679267.8
A110: 26031 | B110: 43042 | C110: Trash - Curbside/Alley Missed Pickup | D110: Missed. | E110: 2731 Murfreesboro Pike | F110: =SEARCH($G$1,D110,1) -> #VALUE! | G110: =SEARCH($G$1,D110,1) -> #VALUE! | S110: 37013 | T110: RED RIVER | U110: 4502 | V110: 32 | W110: 1781139.4 | X110: 632445.6
A111: 26038 | B111: 43042 | C111: Trash - Curbside/Alley Missed Pickup | D111: entire street was missed | E111: 1021 IVERSON AVE | F111: =SEARCH($G$1,D111,1) -> #VALUE! | G111: =SEARCH($G$1,D111,1) -> #VALUE! | S111: 37216 | T111: METRO | U111: 9505 | V111: 8 | W111: 1750814.6 | X111: 683451.99
... A156: 26591 | B156: 43046 | C156: Trash - Backdoor | D156: missed back door - back door | E156: 3040 Ned Shelton Rd | F156: =SEARCH($G$1,D156,1) -> #VALUE! | G156: =SEARCH($G$1,D156,1) -> #VALUE! | S156: 37217 | T156: RED RIVER | U156: 2504 | V156: 29 | W156: 1781246.6 | X156: 641849.9
A157: 26673 | B157: 43046 | C157: Trash - Curbside/Alley Missed Pickup | D157: customer says trash is not being picked up between 101-150 2nd Ave N | E157: 111 2nd Ave N | F157: =SEARCH($G$1,D157,1) -> 24 | G157: =SEARCH($G$1,D157,1) -> 24 | S157: 37201 | T157: Metro | V157: 19 | W157: 1739543.4 | X157: 666600.8
A158: 26674 | B158: 43046 | C158: Trash - Curbside/Alley Missed Pickup | D158: customer says trash is not being picked up between 101-150 2nd Ave N | E158: 111 2nd Ave N | F158: =SEARCH($G$1,D158,1) -> 24 | G158: =SEARCH($G$1,D158,1) -> 24 | S158: 37201 | V158: 19 | W158: 1739543.4 | X158: 666600.8
A159: 26694 | B159: 43046 | C159: Trash Collection Complaint | D159: Trash cart is being left in middle of drive way and at times in the ditch and turn over. She's disable and not able to get out and pickup. Please talk to driver. | E159: 571 Stevenson St | F159: =SEARCH($G$1,D159,1) -> 108 | G159: =SEARCH($G$1,D159,1) -> 108 | S159: 37209 | T159: RED RIVER | U159: 4203 | V159: 20 | W159: 1712804 | X159: 664734.56
A160: 26737 | B160: 43046 | C160: Trash - Backdoor | D160: Back door missed. | E160: 4213 Brush Hill Rd | F160: =SEARCH($G$1,D160,1) -> #VALUE! | G160: =SEARCH($G$1,D160,1) -> #VALUE! | S160: 37216 | T160: RED RIVER | U160: 2203 | V160: 7 | W160: 1757820.8 | X160: 691476.2
A161: 26739 | B161: 43046 | C161: Trash - Curbside/Alley Missed Pickup | D161: Missed. | E161: 3316 Curtis Hill Ct | F161: =SEARCH($G$1,D161,1) -> #VALUE! | G161: =SEARCH($G$1,D161,1) -> #VALUE! | S161: 37218 | T161: RED RIVER | U161: 4204 | V161: 2 | W161: 1723755.4 | X161: 680649.2
A162: 26745 | B162: 43046 | C162: Trash - Curbside/Alley Missed Pickup | D162: Missed. | E162: 1112 Joseph Ave A | F162: =SEARCH($G$1,D162,1) -> #VALUE! | G162: =SEARCH($G$1,D162,1) -> #VALUE! | S162: 37207 | T162: METRO | U162: 9207 | V162: 5 | W162: 1740730.6 | X162: 677098.4
A163: 26746 | B163: 43046 | C163: Trash - Curbside/Alley Missed Pickup | D163: Missed. | E163: 824 Harvest Grove Dr | F163: =SEARCH($G$1,D163,1) -> #VALUE! | G163: =SEARCH($G$1,D163,1) -> #VALUE! | S163: 37013 | V163: 33 | W163: 1789788.4 | X163: 626552.76
A164: 26812 | B164: 43047 | C164: Trash - Curbside/Alley Missed Pickup | D164: Curb Trash/miss one side of street, happen every time. Tuesday | E164: 1917 Valley Park Dr | F164: =SEARCH($G$1,D164,1) -> #VALUE! | G164: =SEARCH($G$1,D164,1) -> #VALUE! | S164: 37216 | T164: RED RIVER | U164: 1203 | V164: 7 | W164: 1758394.1 | X164: 679124.25
A165: 26823 | B165: 43047 | C165: Trash - Backdoor | D165: backdoor pick up missed | E165: 3114 moorewood dr | F165: =SEARCH($G$1,D165,1) -> #VALUE! | G165: =SEARCH($G$1,D165,1) -> #VALUE! | S165: 37207 | T165: RED RIVER | U165: 2202 | V165: 3 | W165: 1738636.2 | X165: 692656.8
...

Sheet Sheet1
A1: Trash Route | B1: count
A2: 3205 | B2: =COUNTIF(trash_hauler_report!U:U,Sheet1!A2) -> 145
A3: 4202 | B3: =COUNTIF(trash_hauler_report!U:U,Sheet1!A3) -> 178
A4: 4205 | B4: =COUNTIF(trash_hauler_report!U:U,Sheet1!A4) -> 72
A5: 2206 | B5: =COUNTIF(trash_hauler_report!U:U,Sheet1!A5) -> 102
A6: 4203 | B6: =COUNTIF(trash_hauler_report!U:U,Sheet1!A6) -> 240
A7: 4304 | B7: =COUNTIF(trash_hauler_report!U:U,Sheet1!A7) -> 267
A8: 3303 | B8: =COUNTIF(trash_hauler_report!U:U,Sheet1!A8) -> 226
A9: 9208 | B9: =COUNTIF(trash_hauler_report!U:U,Sheet1!A9) -> 233
A10: 4210 | B10: =COUNTIF(trash_hauler_report!U:U,Sheet1!A10) -> 35
A11: 4204 | B11: =COUNTIF(trash_hauler_report!U:U,Sheet1!A11) -> 192
A12: 3201 | B12: =COUNTIF(trash_hauler_report!U:U,Sheet1!A12) -> 253
A13: 9207 | B13: =COUNTIF(trash_hauler_report!U:U,Sheet1!A13) -> 84
... A27: 9303 | B27: =COUNTIF(trash_hauler_report!U:U,Sheet1!A27) -> 267
A28: 2303S | B28: =COUNTIF(trash_hauler_report!U:U,Sheet1!A28) -> 24
A29: 3305S | B29: =COUNTIF(trash_hauler_report!U:U,Sheet1!A29) -> 15
A30: 1309 | B30: =COUNTIF(trash_hauler_report!U:U,Sheet1!A30) -> 50
A31: 3504 | B31: =COUNTIF(trash_hauler_report!U:U,Sheet1!A31) -> 161
A32: 9203 | B32: =COUNTIF(trash_hauler_report!U:U,Sheet1!A32) -> 241
A33: 4305 | B33: =COUNTIF(trash_hauler_report!U:U,Sheet1!A33) -> 131
A34: 4403 | B34: =COUNTIF(trash_hauler_report!U:U,Sheet1!A34) -> 190
A35: 4505 | B35: =COUNTIF(trash_hauler_report!U:U,Sheet1!A35) -> 101
A36: 1401 | B36: =COUNTIF(trash_hauler_report!U:U,Sheet1!A36) -> 67
A37: 9401 | B37: =COUNTIF(trash_hauler_report!U:U,Sheet1!A37) -> 101
A38: 3404 | B38: =COUNTIF(trash_hauler_report!U:U,Sheet1!A38) -> 106
A39: 3401 | B39: =COUNTIF(trash_hauler_report!U:U,Sheet1!A39) -> 164
A40: 3301S | B40: =COUNTIF(trash_hauler_report!U:U,Sheet1!A40) -> 4
A41: 3302S | B41: =COUNTIF(trash_hauler_report!U:U,Sheet1!A41) -> 23
A42: 2403 | B42: =COUNTIF(trash_hauler_report!U:U,Sheet1!A42) -> 138
A43: 1404 | B43: =COUNTIF(trash_hauler_report!U:U,Sheet1!A43) -> 88
A44: 1504 | B44: =COUNTIF(trash_hauler_report!U:U,Sheet1!A44) -> 136
A45: 4401 | B45: =COUNTIF(trash_hauler_report!U:U,Sheet1!A45) -> 78
A46: 9508 | B46: =COUNTIF(trash_hauler_report!U:U,Sheet1!A46) -> 140
A47: 3203 | B47: =COUNTIF(trash_hauler_report!U:U,Sheet1!A47) -> 262
A48: 4504 | B48: =COUNTIF(trash_hauler_report!U:U,Sheet1!A48) -> 359
A49: 4402 | B49: =COUNTIF(trash_hauler_report!U:U,Sheet1!A49) -> 115
A50: 2505 | B50: =COUNTIF(trash_hauler_report!U:U,Sheet1!A50) -> 218
A51: 2501 | B51: =COUNTIF(trash_hauler_report!U:U,Sheet1!A51) -> 116
A52: 2509 | B52: =COUNTIF(trash_hauler_report!U:U,Sheet1!A52) -> 87
A53: 9504 | B53: =COUNTIF(trash_hauler_report!U:U,Sheet1!A53) -> 59
... A79: 4301 | B79: =COUNTIF(trash_hauler_report!U:U,Sheet1!A79) -> 86
A80: 2304S | B80: =COUNTIF(trash_hauler_report!U:U,Sheet1!A80) -> 27
A81: 9307 | B81: =COUNTIF(trash_hauler_report!U:U,Sheet1!A81) -> 115
A82: 1505 | B82: =COUNTIF(trash_hauler_report!U:U,Sheet1!A82) -> 95
A83: 3306 | B83: =COUNTIF(trash_hauler_report!U:U,Sheet1!A83) -> 125
A84: 3303S | B84: =COUNTIF(trash_hauler_report!U:U,Sheet1!A84) -> 2
A85: 4404 | B85: =COUNTIF(trash_hauler_report!U:U,Sheet1!A85) -> 274
A86: 4409 | B86: =COUNTIF(trash_hauler_report!U:U,Sheet1!A86) -> 80
A87: 4407 | B87: =COUNTIF(trash_hauler_report!U:U,Sheet1!A87) -> 71
A88: 1503 | B88: =COUNTIF(trash_hauler_report!U:U,Sheet1!A88) -> 196
A89: 2304 | B89: =COUNTIF(trash_hauler_report!U:U,Sheet1!A89) -> 62
A90: 2207 | B90: =COUNTIF(trash_hauler_report!U:U,Sheet1!A90) -> 24
A91: 2204 | B91: =COUNTIF(trash_hauler_report!U:U,Sheet1!A91) -> 126
A92: 2205 | B92: =COUNTIF(trash_hauler_report!U:U,Sheet1!A92) -> 145
A93: 1202 | B93: =COUNTIF(trash_hauler_report!U:U,Sheet1!A93) -> 104
A94: 9206 | B94: =COUNTIF(trash_hauler_report!U:U,Sheet1!A94) -> 54
A95: 3208 | B95: =COUNTIF(trash_hauler_report!U:U,Sheet1!A95) -> 119
A96: 3202 | B96: =COUNTIF(trash_hauler_report!U:U,Sheet1!A96) -> 245
... A101: 9301 | B101: =COUNTIF(trash_hauler_report!U:U,Sheet1!A101) -> 49
A102: 3304S | B102: =COUNTIF(trash_hauler_report!U:U,Sheet1!A102) -> 45
A103: 3402 | B103: =COUNTIF(trash_hauler_report!U:U,Sheet1!A103) -> 97
A104: 2305S | B104: =COUNTIF(trash_hauler_report!U:U,Sheet1!A104) -> 47
A105: 1502 | B105: =COUNTIF(trash_hauler_report!U:U,Sheet1!A105) -> 125
A106: 1402 | B106: =COUNTIF(trash_hauler_report!U:U,Sheet1!A106) -> 127
A107: 3505 | B107: =COUNTIF(trash_hauler_report!U:U,Sheet1!A107) -> 79
A108: 3207 | B108: =COUNTIF(trash_hauler_report!U:U,Sheet1!A108) -> 155
A109: 4503 | B109: =COUNTIF(trash_hauler_report!U:U,Sheet1!A109) -> 160
A110: 4508 | B110: =COUNTIF(trash_hauler_report!U:U,Sheet1!A110) -> 39
A111: 3307 | B111: =COUNTIF(trash_hauler_report!U:U,Sheet1!A111) -> 149
A112: 4410 | B112: =COUNTIF(trash_hauler_report!U:U,Sheet1!A112) -> 39
A113: 9205 | B113: =COUNTIF(trash_hauler_report!U:U,Sheet1!A113) -> 151
A114: 9404 | B114: =COUNTIF(trash_hauler_report!U:U,Sheet1!A114) -> 108
A115: 9308 | B115: =COUNTIF(trash_hauler_report!U:U,Sheet1!A115) -> 128
A116: 9406 | B116: =COUNTIF(trash_hauler_report!U:U,Sheet1!A116) -> 79
... A121: 1507 | B121: =COUNTIF(trash_hauler_report!U:U,Sheet1!A121) -> 15
A122: 3402S | B122: =COUNTIF(trash_hauler_report!U:U,Sheet1!A122) -> 17
A123: 9204 | B123: =COUNTIF(trash_hauler_report!U:U,Sheet1!A123) -> 55
A124: 9302 | B124: =COUNTIF(trash_hauler_report!U:U,Sheet1!A124) -> 96
A125: 2302 | B125: =COUNTIF(trash_hauler_report!U:U,Sheet1!A125) -> 84
A126: 2401 | B126: =COUNTIF(trash_hauler_report!U:U,Sheet1!A126) -> 131
A127: 1403 | B127: =COUNTIF(trash_hauler_report!U:U,Sheet1!A127) -> 80
A128: 2405 | B128: =COUNTIF(trash_hauler_report!U:U,Sheet1!A128) -> 231
A129: 4405 | B129: =COUNTIF(trash_hauler_report!U:U,Sheet1!A129) -> 131
A130: 9502 | B130: =COUNTIF(trash_hauler_report!U:U,Sheet1!A130) -> 90
A131: 4507 | B131: =COUNTIF(trash_hauler_report!U:U,Sheet1!A131) -> 77
A132: 9202 | B132: =COUNTIF(trash_hauler_report!U:U,Sheet1!A132) -> 87
A133: 4203S | B133: =COUNTIF(trash_hauler_report!U:U,Sheet1!A133) -> 58
A134: 9304 | B134: =COUNTIF(trash_hauler_report!U:U,Sheet1!A134) -> 72
A135: 1204 | B135: =COUNTIF(trash_hauler_report!U:U,Sheet1!A135) -> 77
A136: 1303 | B136: =COUNTIF(trash_hauler_report!U:U,Sheet1!A136) -> 286
A137: 2308 | B137: =COUNTIF(trash_hauler_report!U:U,Sheet1!A137) -> 94
A138: 3403 | B138: =COUNTIF(trash_hauler_report!U:U,Sheet1!A138) -> 155
A139: 2306 | B139: =COUNTIF(trash_hauler_report!U:U,Sheet1!A139) -> 44
A140: 4310 | B140: =COUNTIF(trash_hauler_report!U:U,Sheet1!A140) -> 46
A141: 3405 | B141: =COUNTIF(trash_hauler_report!U:U,Sheet1!A141) -> 109
A142: 4506 | B142: =COUNTIF(trash_hauler_report!U:U,Sheet1!A142) -> 31
A143: 3501 | B143: =COUNTIF(trash_hauler_report!U:U,Sheet1!A143) -> 137
A144: 2506 | B144: =COUNTIF(trash_hauler_report!U:U,Sheet1!A144) -> 71
A145: 1205 | B145: =COUNTIF(trash_hauler_report!U:U,Sheet1!A145) -> 45
... A148: 9305 | B148: =COUNTIF(trash_hauler_report!U:U,Sheet1!A148) -> 13
...

Sheet Sheet4
A1: Trash Route | B1: count
A2: 4504 | B2: 359
A3: 3302 | B3: 310
A4: 1303 | B4: 286
A5: 1301 | B5: 275
A6: 4404 | B6: 274
A7: 1304 | B7: 273
A8: 4304 | B8: 267
A9: 9303 | B9: 267
A10: 3203 | B10: 262
A11: 3412 | B11: 255
A12: 3305 | B12: 254
A13: 3201 | B13: 253
... A125: 1308 | B125: 58
A126: 4203S | B126: 58
A127: 9204 | B127: 55
A128: 9206 | B128: 54
A129: 9306 | B129: 54
A130: 1309 | B130: 50
A131: 1405 | B131: 50
A132: 2402 | B132: 49
A133: 9301 | B133: 49
A134: 2305S | B134: 47
A135: 2408 | B135: 46
A136: 4310 | B136: 46
A137: 3304S | B137: 45
A138: 1205 | B138: 45
A139: 2306 | B139: 44
A140: 3206 | B140: 42
A141: 9501 | B141: 39
A142: 4508 | B142: 39
A143: 4410 | B143: 39
A144: 4210 | B144: 35
A145: 9405 | B145: 34
A146: 1302S | B146: 34
A147: 4506 | B147: 31
A148: 3406 | B148: 28
A149: 2304S | B149: 27
A150: 4209 | B150: 27
A151: 2303S | B151: 24
A152: 2207 | B152: 24
A153: 3302S | B153: 23
A154: 3407 | B154: 20
A155: 3402S | B155: 17
A156: 3305S | B156: 15
A157: 1507 | B157: 15
A158: 9305 | B158: 13
A159: 1303S | B159: 9
A160: 1504S | B160: 9
A161: 2301S | B161: 7
A162: 3411 | B162: 7
A163: 4305S | B163: 6
A164: 2402S | B164: 5
A165: 3301S | B165: 4
A166: 1202S | B166: 4
A167: 4402S | B167: 4
A168: 2405S | B168: 3
A169: 4504S | B169: 3
A170: 4201S | B170: 3
A171: 3303S | B171: 2
A172: 2505S | B172: 2
A173: 1502S | B173: 2
A174: 2201S | B174: 1

Sheet Sheet2
A1: Incident Address
A2: 3817 Crouch Dr | B2: =COUNTIF(trash_hauler_report!$E$2:$E$20227,Sheet2!A2) -> 1
A3: 4028 Clarksville Pike | B3: =COUNTIF(trash_hauler_report!$E$2:$E$20227,Sheet2!A3) -> 3
A4: 6528 Thunderbird Dr | B4: =COUNTIF(trash_hauler_report!$E$2:$E$20227,Sheet2!A4) -> 1
A5: 2603 old matthews rd | B5: =COUNTIF(trash_hauler_report!$E$2:$E$20227,Sheet2!A5) -> 1
A6: 604 croley dr | B6: =COUNTIF(trash_hauler_report!$E$2:$E$20227,Sheet2!A6) -> 1
A7: 3602 floral dr | B7: =COUNTIF(trash_hauler_report!$E$2:$E$20227,Sheet2!A7) -> 5
A8: 4721 Chalmers Dr | B8: =COUNTIF(trash_hauler_report!$E$2:$E$20227,Sheet2!A8) -> 1
A9: 1816 Jo Johnston Ave | B9: =COUNTIF(trash_hauler_report!$E$2:$E$20227,Sheet2!A9) -> 18
A10: 4484 Lavergne Couchville Pike | B10: =COUNTIF(trash_hauler_report!$E$2:$E$20227,Sheet2!A10) -> 1
A11: 1206 Ireland St | B11: =COUNTIF(trash_hauler_report!$E$2:$E$20227,Sheet2!A11) -> 1
A12: 3113 HYDES FERRY RD | B12: =COUNTIF(trash_hauler_report!$E$2:$E$20227,Sheet2!A12) -> 1
A13: 3210 Whites Creek Pike | B13: =COUNTIF(trash_hauler_report!$E$2:$E$20227,Sheet2!A13) -> 9
... A4390: 2322 Modena Dr | B4390: =COUNTIF(trash_hauler_report!$E$2:$E$20227,Sheet2!A4390) -> 1
A4391: 107 | B4391: =COUNTIF(trash_hauler_report!$E$2:$E$20227,Sheet2!A4391) -> 1
A4392: 6004 Monroe Xing | B4392: =COUNTIF(trash_hauler_report!$E$2:$E$20227,Sheet2!A4392) -> 1
A4393: 717 Ansley Ct | B4393: =COUNTIF(trash_hauler_report!$E$2:$E$20227,Sheet2!A4393) -> 1
A4394: 1919 Blair Blvd | B4394: =COUNTIF(trash_hauler_report!$E$2:$E$20227,Sheet2!A4394) -> 3
A4395: 312 NEELYS BEND RD | B4395: =COUNTIF(trash_hauler_report!$E$2:$E$20227,Sheet2!A4395) -> 6
A4396: 4149 Highlander Ct | B4396: =COUNTIF(trash_hauler_report!$E$2:$E$20227,Sheet2!A4396) -> 1
A4397: 1227 Kirkland Ave | B4397: =COUNTIF(trash_hauler_report!$E$2:$E$20227,Sheet2!A4397) -> 1
A4398: 1612 Porter Ave | B4398: =COUNTIF(trash_hauler_report!$E$2:$E$20227,Sheet2!A4398) -> 2
A4399: 429 Franklin Limestone Rd | B4399: =COUNTIF(trash_hauler_report!$E$2:$E$20227,Sheet2!A4399) -> 2
A4400: 2321 23rd Ave N | B4400: =COUNTIF(trash_hauler_report!$E$2:$E$20227,Sheet2!A4400) -> 2
A4401: 1612 24TH AVE N | B4401: =COUNTIF(trash_hauler_report!$E$2:$E$20227,Sheet2!A4401) -> 2
A4402: 912 38th Ave N | B4402: =COUNTIF(trash_hauler_report!$E$2:$E$20227,Sheet2!A4402) -> 2
A4403: 716 EBENWAY DR | B4403: =COUNTIF(trash_hauler_report!$E$2:$E$20227,Sheet2!A4403) -> 1
... A12381: 604 Somerset Ct | B12381: =COUNTIF(trash_hauler_report!$E$2:$E$20227,Sheet2!A12381) -> 1

Sheet Sheet3
A1: Incident | B1: Address
A2: 3817 | B2: Crouch | C2: Dr
A3: 4028 | B3: Clarksville | C3: Pike
A4: 6528 | B4: Thunderbird | C4: Dr
A5: 2603 | B5: old | C5: matthews | D5: rd
A6: 604 | B6: croley | C6: dr
A7: 3602 | B7: floral | C7: dr
A8: 4721 | B8: Chalmers | C8: Dr
A9: 1816 | B9: Jo | C9: Johnston | D9: Ave
A10: 4484 | B10: Lavergne | C10: Couchville | D10: Pike
A11: 1206 | B11: Ireland | C11: St
A12: 3113 | B12: HYDES | C12: FERRY | D12: RD
A13: 3210 | B13: Whites | C13: Creek | D13: Pike
A14: 830 | B14: Meridian | C14: St
A15: 2200 | B15: osage | C15: st
A16: 6543 | B16: Thunderbird | C16: Dr
A17: 2218 | B17: BUENA | C17: VISTA | D17: PIKE
A18: 2720 | B18: riverbend | C18: dr
A19: 4209 | B19: Lone | C19: Oak | D19: Rd
A20: 356 | B20: Kingview | C20: Dr
A21: 449 | B21: Westboro | C21: Dr
A22: 1414 | B22: Old | C22: Hickory | D22: Blvd
A23: 117 | B23: Lafayette | C23: Ct
A24: 1904 | B24: MeHarry | C24: Blvd
A25: 1144 | B25: Sewanee | C25: Rd
A26: 1815 | B26: WOODMONT | C26: BLVD
A27: 405 | B27: Page | C27: Rd
A28: 4722 | B28: DANBY | C28: DR
A29: 2812 | B29: 27TH | C29: AVE | D29: S
A30: 4506 | B30: DAKOTA | C30: AVE
A31: 259 | B31: Sunrise | C31: Ave
A32: 4311 | B32: dakota | C32: ave
A33: 4029 | B33: Graybar | C33: Ct
A34: 524 | B34: Harding | C34: Pl
A35: 3702 | B35: Hobbs | C35: Rd
A36: 405 | B36: brook | C36: hollow | D36: rd
A37: 162 | B37: antioch | C37: pike
A38: 131 | B38: page | C38: rd
A39: 3704 | B39: Hobbs | C39: Rd
A40: 6011 | B40: Jocelyn | C40: Hollow | D40: Rd
A41: 2524 | B41: Batavia | C41: St
A42: 934 | B42: Battery | C42: Ln
A43: 305 | B43: Williams | C43: Ct
A44: 346 | B44: lynn | C44: dr
A45: 4205 | B45: arundel | C45: ct
A46: 204 | B46: Channelkirk | C46: Ln
A47: 200 | B47: Channelkirk | C47: Ln
A48: 101 | B48: Westover | C48: Park | D48: Ct
A49: 201 | B49: Channelkirk | C49: Ln
A50: 205 | B50: Channelkirk | C50: Ln
A51: 4309 | B51: Lone | C51: Oak | D51: Rd
A52: 4507 | B52: Nevada | C52: Ave
A53: 3012 | B53: Sunnyview | C53: Ct
A54: 118 | B54: WESTOVER | C54: PARK | D54: CT
A55: 607 | B55: 40th | C55: Ave | D55: N
A56: 3041 | B56: Fieldstone | C56: Dr
A57: 1413 | B57: Montgomery | C57: Ave
A58: 962 | B58: battery | C58: ln
A59: 103 | B59: Page | C59: Rd
A60: 905 | B60: woodmont | C60: blvd
A61: 114 | B61: Lasalle | C61: Ct | D61: B
A62: 732 | B62: Ridgeview | C62: Ct
A63: 2323 | B63: Merry | C63: St
A64: 4625 | B64: long | C64: br
A65: 816 | B65: Elissa | C65: Dr
A66: 608 | B66: CLEVELAND | C66: ST
A67: 2015 | B67: Beech | C67: Ave | D67: B
A68: 116 | B68: Bart | C68: Dr
A69: 5115 | B69: Greentree | C69: Dr
A70: 4104 | B70: Coleridge | C70: Dr
A71: 362 | B71: ardsley | C71: pl
A72: 4828 | B72: Cimarron | C72: Way
A73: 496 | B73: Whispering | C73: Hills | D73: Dr
A74: Robin | B74: Springs | C74: Rd
A75: 1711 | B75: Glen | C75: Echo | D75: Rd | E75: A
A76: 611 | B76: Farrell | C76: Pkwy
A77: 531 | B77: Cathy | C77: Jo | D77: Cir
A78: 427 | B78: West | C78: Bend | D78: Dr
A79: 2005 | B79: Lebanon | C79: Pike
A80: 5900 | B80: Cloverland | C80: Dr
A81: 115 | B81: Rosa | C81: L | D81: Parks | E81: BLvd
A82: 1112 | B82: Joseph | C82: Ave | D82: A
A83: 1800 | B83: fatherland | C83: st
A84: 615 | B84: 39th | C84: Ave | D84: N
A85: 6532 | B85: cornwall | C85: ct
A86: 1801 | B86: Shelby | C86: Ave | D86: B
A87: 4225 | B87: Eatons | C87: Creek | D87: Rd
A88: 1300 | B88: Rural | C88: Hill | D88: Rd
A89: 5001 | B89: Stillwood | C89: dr
A90: 5040 | B90: Mclendon | C90: Dr
A91: 15482 | B91: Old | C91: Hickory | D91: Blvd
A92: 5209 | B92: nevada | C92: ave
A93: 2413 | B93: ravine | C93: dr
A94: 641 | B94: truxton | C94: ct
A95: 916 | B95: Petway | C95: Ave
A96: 914 | B96: Petway | C96: Ave
A97: 2205 | B97: woodmont | C97: blvd
A98: 1619 | B98: HEIMAN | C98: ST
A99: 1209 | B99: Linden | C99: Ave
A100: 1609 | B100: Lillian | C100: St
...

Sheet trash_hauler_report_project_not
A1: MISSED | B1: OTHERS
A2: missed | B2: damaged | C2: email reminder | D2: supverisor | E2: close lid | F2: backdoor service? | G2: full trash | H2: trash scattered
A3: miss
A4: skip | C4: word map of the 'not missed trash'
A5: skipped
A6: not picked
A7: picked up
A8: failed
A9: did not
A10: fail
A11: failed
A12: forgot
A13: never
